[
    {
        "number": "",
        "text": "137. Псалмів"
    },
    {
        "number": 1,
        "text": "Над річками Вавилонськими, там ми сиділи та й плакали, коли згадували про Сіона!"
    },
    {
        "number": 2,
        "text": "На вербах у ньому повісили ми свої арфи,"
    },
    {
        "number": 3,
        "text": "співу бо пісні від нас там жадали були поневолювачі наші, а веселощів наші мучителі: Заспівайте но нам із Сіонських пісень!"
    },
    {
        "number": 4,
        "text": "Як же зможемо ми заспівати Господнюю пісню в землі чужинця?"
    },
    {
        "number": 5,
        "text": "Якщо я забуду за тебе, о Єрусалиме, хай забуде за мене правиця моя!"
    },
    {
        "number": 6,
        "text": "Нехай мій язик до мого піднебіння прилипне, якщо я не буду тебе пам'ятати, якщо не поставлю я Єрусалима над радість найвищу свою!..."
    },
    {
        "number": 7,
        "text": "Пам'ятай же, о Господи, едомським синам про день Єрусалиму, як кричали вони: Руйнуйте, руйнуйте аж до підвалин його!..."
    },
    {
        "number": 8,
        "text": "Вавилонськая дочко, що маєш і ти ограбована бути, блажен, хто заплатить тобі за твій чин, що ти нам заподіяла!"
    },
    {
        "number": 9,
        "text": "Блажен, хто ухопить та порозбиває об скелю і твої немовлята!..."
    }
]