[
    {
        "number": "",
        "text": "84. Псалмів"
    },
    {
        "number": 1,
        "text": "Для дириґетна хору. На ґітійськомім знарядді. Синів Кореєвих. Псалом. (84-2) Які любі оселі Твої, Господи Саваоте!"
    },
    {
        "number": 2,
        "text": "(84-3) Затужена та омліває душа моя за подвір'ями Господа, моє серце та тіло моє линуть до Бога Живого!"
    },
    {
        "number": 3,
        "text": "(84-4) і пташка знаходить домівку, і кубло собі ластівка, де кладе пташенята свої, при жертівниках Твоїх, Господи Саваоте, Царю мій і Боже мій!"
    },
    {
        "number": 4,
        "text": "(84-5) Блаженні, хто мешкає в домі Твоїм, вони будуть повіки хвалити Тебе! Села."
    },
    {
        "number": 5,
        "text": "(84-6) Блаженна людина, що в Тобі має силу свою, блаженні, що в їхньому серці дороги до Тебе,"
    },
    {
        "number": 6,
        "text": "(84-7) ті, що через долину Плачу переходять, чинять її джерелом, і дощ ранній дає благословення!"
    },
    {
        "number": 7,
        "text": "(84-8) Вони ходять від сили до сили, і показуються перед Богом у Сіоні."
    },
    {
        "number": 8,
        "text": "(84-9) Господи, Боже Саваоте, послухай молитву мою, почуй, Боже Яковів! Села."
    },
    {
        "number": 9,
        "text": "(84-10) Щите наш, поглянь же, о Боже, і придивись до обличчя Свого помазанця!"
    },
    {
        "number": 10,
        "text": "(84-11) Ліпший бо день на подвір'ях Твоїх, аніж тисяча в іншому місці, я б вибрав сидіти при порозі дому Бога мого, аніж жити в наметах безбожности!"
    },
    {
        "number": 11,
        "text": "(84-12) Бо сонце та щит Господь, Бог! Господь дає милість та славу, добра не відмовляє усім, хто в невинності ходить."
    },
    {
        "number": 12,
        "text": "(84-13) Господи Саваоте, блаженна людина, що на Тебе надіється!"
    }
]