[
    {
        "number": "",
        "text": "15. Псалмів"
    },
    {
        "number": 1,
        "text": "Псалом Давидів. Господи, хто може перебувати в наметі Твоїм? Хто мешкати може на святій Твоїй горі?"
    },
    {
        "number": 2,
        "text": "Той, хто в невинності ходить, і праведність чинить, і правду говорить у серці своїм,"
    },
    {
        "number": 3,
        "text": "хто не обмовляє своїм язиком, і злого не чинить для друга свого, і свого ближнього не зневажає!"
    },
    {
        "number": 4,
        "text": "Обридливий погорджений в очах його, і він богобійних шанує, присягає, для себе хоча б і на зло, і дотримує;"
    },
    {
        "number": 5,
        "text": "не дає свого срібла на лихву, і не бере на невинного підкупу. Хто чинить таке, ніколи той не захитається!"
    }
]