[
    {
        "number": "",
        "text": "129. Псалмів"
    },
    {
        "number": 1,
        "text": "Пісня прочан. Багато гнобили мене від юнацтва мого, нехай но ізраїль повість!"
    },
    {
        "number": 2,
        "text": "Багато гнобили мене від юнацтва мого, та мене не подужали!"
    },
    {
        "number": 3,
        "text": "Орали були на хребті моїм плугатарі, поклали вони довгі борозни,"
    },
    {
        "number": 4,
        "text": "та Господь справедливий, Він шнури безбожних порвав!"
    },
    {
        "number": 5,
        "text": "Нехай посоромлені будуть, і хай повідступають назад усі ті, хто Сіона ненавидить!"
    },
    {
        "number": 6,
        "text": "Бодай стали вони, як трава на дахах, що всихає вона, поки виросте,"
    },
    {
        "number": 7,
        "text": "що нею жмені своєї жнець не наповнить, ані оберемка свого в'язальник,"
    },
    {
        "number": 8,
        "text": "і не скаже прохожий до них: Благословення Господнє на вас, благословляємо вас ім'ям Господа!"
    }
]